{"type":"object","properties":{"id":{"type":"string","format":"uuid","readOnly":true},"purpose":{"enum":["appointment_booking","notifications_email","notifications_push","notifications_sms","marketing","data_analytics"],"type":"string","description":"* `appointment_booking` - Agendamento de Consultas\n* `notifications_email` - Notificações por Email\n* `notifications_push` - Notificações Push\n* `notifications_sms` - Notificações SMS\n* `marketing` - Comunicações de Marketing\n* `data_analytics` - Uso de Dados para Analytics","x-readme-ref-name":"ConsentRecordPurposeEnum"},"purpose_display":{"type":"string","readOnly":true},"granted":{"type":"boolean"},"granted_at":{"type":"string","format":"date-time","readOnly":true,"nullable":true},"revoked_at":{"type":"string","format":"date-time","readOnly":true,"nullable":true},"created_at":{"type":"string","format":"date-time","readOnly":true},"updated_at":{"type":"string","format":"date-time","readOnly":true}},"required":["created_at","granted_at","id","purpose","purpose_display","revoked_at","updated_at"],"x-readme-ref-name":"ConsentRecord"}